aura_tools/__init__.py
aura_tools/code_explanation_generator.py
aura_tools/comment_insert.py
aura_tools/count_functions.py
aura_tools/director_scanner.py
aura_tools/github_repository_downloader.py
aura_tools/java_function_extractor.py
aura_tools/json_file_util.py
aura_tools/llm/__init__.py
aura_tools/llm/baidu_ai_client.py
aura_tools/llm/deepseek_ai_client.py
aura_tools/llm/tongyi_ai_client.py
aura_tools/llm/base/__init__.py
aura_tools/llm/base/llm_base_client.py
aura_tools/process/__init__.py
aura_tools/process/multi_process_handler.py
aura_tools/thread/__init__.py
aura_tools/thread/multi_thread_handler.py
aura_tools-0.27.dist-info/LICENSE
aura_tools-0.27.dist-info/METADATA
aura_tools-0.27.dist-info/WHEEL
aura_tools-0.27.dist-info/entry_points.txt
aura_tools-0.27.dist-info/top_level.txt
aura_tools-0.27.dist-info/RECORD
